slideseg/Annotation_Key.txt
slideseg/Parameters.txt
slideseg/__init__.py
slideseg-1.1.data/scripts/slideseg-run
slideseg-1.1.dist-info/DESCRIPTION.rst
slideseg-1.1.dist-info/METADATA
slideseg-1.1.dist-info/RECORD
slideseg-1.1.dist-info/WHEEL
slideseg-1.1.dist-info/metadata.json
slideseg-1.1.dist-info/top_level.txt
