Metadata-Version: 2.0
Name: slideseg
Version: 1.1
Summary: segments whole slide images into usable image chips and masks for deep learning
Home-page: https://github.com/btcrabb/SlideSeg
Author: bcrabb
Author-email: brendancrabb8388@pointloma.edu
License: MIT
Platform: UNKNOWN
Classifier: Development Status :: 3 - Alpha
Classifier: License :: OSI Approved :: MIT License
Classifier: Programming Language :: Python :: 2.7
Requires-Dist: numpy
Requires-Dist: opencv-python
Requires-Dist: openslide-python
Requires-Dist: pexif
Requires-Dist: tqdm
